shieldapi/__init__.py
shieldapi/keycloak_utils.py
shieldapi/frameworks/__init__.py
shieldapi/frameworks/fastapi.py
shieldapi/frameworks/flask.py
shieldapi-2.1.0.dist-info/licenses/LICENSE
tests/__init__.py
tests/conftest.py
tests/mock.py
tests/test_fastapi.py
tests/test_flask.py
tests/test_keycloak_utils.py
shieldapi-2.1.0.dist-info/METADATA
shieldapi-2.1.0.dist-info/WHEEL
shieldapi-2.1.0.dist-info/top_level.txt
shieldapi-2.1.0.dist-info/RECORD
