Metadata-Version: 2.4
Name: shieldapi
Version: 2.1.0
Summary: A package for endpoint protection of APIs using Keycloak
Author: SINTEF, Fraunhofer IWM
Author-email: yoav.nahshon@iwm.fraunhofer.de
Classifier: Programming Language :: Python :: 3
Classifier: License :: OSI Approved :: BSD License
Classifier: Operating System :: OS Independent
Requires-Python: >=3.6
License-File: LICENSE
Requires-Dist: python-keycloak>=1
Requires-Dist: flask<3.0,>=2.2.3
Requires-Dist: fastapi<1.0,>=0.85.0
Provides-Extra: dev
Requires-Dist: bumpver==2021.1114; extra == "dev"
Requires-Dist: dunamai==1.7.0; extra == "dev"
Requires-Dist: pre-commit~=4.3.0; extra == "dev"
Provides-Extra: tests
Requires-Dist: pytest<8.0,>=7.1.3; extra == "tests"
Requires-Dist: requests-mock<2.0,>=1.10.0; extra == "tests"
Requires-Dist: httpx<1.0,>=0.23.3; extra == "tests"
Requires-Dist: semver<3.0,>=2.13.0; extra == "tests"
Requires-Dist: pytest-mock>=3.10.0; extra == "tests"
Dynamic: license-file
